{"run_number": "1655815368365864", "step_name": "start", "task_id": "1", "attempt_id": 0, "name": "_current_step", "content_type": "gzip+pickle-v2", "type": "metaflow.artifact", "sha": "01b168d0b2c70f906b295772af9efb98b0797cae", "ds_type": "local", "location": ":root:/Users/sylvain/Desktop/dev/otosense/plunk/plunk/sb/metaflow_practice/.metaflow", "flow_id": "ClassifierTrainFlow", "user_name": "sylvain", "tags": [], "system_tags": ["python_version:3.8.11", "runtime:dev", "metaflow_version:2.7.1", "user:sylvain"], "ts_epoch": 1655815369710}